{"poster":"MHQ V1per","date":"2019-06-18T19:09:05.469+0000","title":"Gold / Platin ADC sucht Team","subforum":"Clans & Teams","up_votes":1,"down_votes":0,"body":"Hallo zusammen,\r\n\r\nich suche ein Team welches sich als Ziel setzt kompetitive was zu erreichen.\r\n\r\nDurch Spielen in mehreren Teams habe ich schon etliche Erfahrung im Team errungen und ebenfalls Erfolge erzielt.\r\n\r\nZu mir:\r\n\r\n- anpassbarer Character \r\n- Meta-Championpool\r\n- genug Zeit\r\n- 20 Jahre\r\n- TS \r\n- Erfahrung im Team \r\n\r\nFalls ich in euer Team passen könnte, würde ich mich über ein Gespräch freuen um letzte Information bzw. Fragen beiderseits zu klären.\r\n\r\nDanke euch\r\nVTG Blayzs","replies":[]}