{"poster":"Nata","date":"2016-12-04T04:59:48.127+0000","title":"Replays","subforum":"Problemas Técnicos","up_votes":1,"down_votes":0,"body":"Con que programa se abren cuando las veo desde Documentos? Son .rolf","replies":[{"poster":"KarmaUnder","date":"2016-12-04T05:19:49.074+0000","up_votes":1,"down_votes":0,"body":"con el modo espectador del cliente del lol :v","replies":[]},{"poster":"Excorpion","date":"2016-12-04T06:04:52.595+0000","up_votes":1,"down_votes":1,"body":"Se abren con el lol, pero el sistema aún no lo hace automático.","replies":[]}]}