{"poster":"Hi Im Sion Baby","date":"2018-04-10T16:28:10.384+0000","title":"Holas","subforum":"Charlas Generales","up_votes":2,"down_votes":0,"body":"Jolo a alguien mas le ah pasado este bug del cliente https://imgur.com/a/UmNEW","replies":[{"poster":"No me extrañen","date":"2018-04-10T18:30:59.098+0000","up_votes":1,"down_votes":0,"body":"Si, a mi me pasa, pero tenes que correrlo como si estuviera ahí y listo xd","replies":[]},{"poster":"DIOS TUTI","date":"2018-04-10T17:27:40.285+0000","up_votes":1,"down_votes":0,"body":"mainkra.","replies":[]},{"poster":"Salvor","date":"2018-04-10T17:02:06.018+0000","up_votes":1,"down_votes":0,"body":"Solo a vos te pasa ese bug jajajaja\n\n{{sticker:sg-miss-fortune}} \nSalu2","replies":[]},{"poster":"ZeNch","date":"2018-04-10T16:29:25.394+0000","up_votes":1,"down_votes":0,"body":"tenes que desinstalar el minecraft o probar esto: https://support.riotgames.com/hc/es/articles/224826367-Resoluci%C3%B3n-autom%C3%A1tica-de-problemas-Herramienta-de-reparaci%C3%B3n-hextech","replies":[{"poster":"Hi Im Sion Baby","date":"2018-04-10T16:30:16.981+0000","up_votes":1,"down_votes":0,"body":"> [{quoted}](name=ZeNch,realm=LAS,application-id=v7qsfXsE,discussion-id=w8YP9bkv,comment-id=0000,timestamp=2018-04-10T16:29:25.394+0000)\n>\n> tenes que desinstalar el minecraft o probar esto: https://support.riotgames.com/hc/es/articles/224826367-Resoluci%C3%B3n-autom%C3%A1tica-de-problemas-Herramienta-de-reparaci%C3%B3n-hextech\n\naaah te mamaste xDxD","replies":[{"poster":"ZeNch","date":"2018-04-10T16:37:42.075+0000","up_votes":1,"down_votes":0,"body":"intenta lo segundo pero lo primero no estaria demas","replies":[]}]}]}]}