{"poster":"proyecto InSec","date":"2017-09-27T22:39:54.301+0000","title":"se busca gente para sacar honor xD","subforum":"Reclutamiento","up_votes":1,"down_votes":13,"body":"AGREGUENME Y JUGAMOS","replies":[{"poster":"xSparkz","date":"2017-09-27T23:01:46.850+0000","up_votes":2,"down_votes":0,"body":"Juega bien, asiste al equipo y se buena onda para que te den mas honores","replies":[]},{"poster":"AJ             J","date":"2017-09-27T22:49:11.722+0000","up_votes":2,"down_votes":0,"body":"El honor que te da tu premade vale casi nada comparado con el honor que te dan los randoms.\n\nTe recomiendo jugar algunas partidas de soporte y dedicarte a ayudar al resto, mantener una actitud activamente positiva ayuda mucho (\"Buen gank, gracias.\" / \"GJ Bot.\" / \"Gracias jg por el blue-red\" / \"gg wp\").\n\nEl honor va a caer por si solo.","replies":[]},{"poster":"Kawatori","date":"2017-09-27T22:47:36.604+0000","up_votes":2,"down_votes":0,"body":"Asi no funciona el honor amigo mio. {{sticker:sg-miss-fortune}}","replies":[]},{"poster":"MILFortune","date":"2017-09-27T22:45:25.817+0000","up_votes":1,"down_votes":0,"body":"El honor no stackea aditivamente :v","replies":[]}]}