{"poster":"The Accelerator","date":"2017-09-19T22:37:03.989+0000","title":"Suchen Jungler, Platin (bevorzugt) Vienna Challenger Arena","subforum":"Battlegrounds-Turniere","up_votes":1,"down_votes":0,"body":"Sind 4 Leute und suchen einen Platin Jungler","replies":[{"poster":"KendyKing1","date":"2017-09-25T12:47:48.846+0000","up_votes":1,"down_votes":0,"body":"hi wäre g1 jungler","replies":[]},{"poster":"Fergus CH","date":"2017-09-22T09:09:15.308+0000","up_votes":1,"down_votes":0,"body":"Ich hätte Interesse.\nAktuell Gold 4 (am climben) ;)","replies":[]},{"poster":"yeyyyy","date":"2017-09-20T19:41:57.803+0000","up_votes":1,"down_votes":0,"body":"Frage: Wiso sucht ihr einen Platin Jungler wenn ihr selbst alle G5-P5 Elo seid?","replies":[]},{"poster":"Honeybrätscher","date":"2017-09-19T23:53:05.941+0000","up_votes":1,"down_votes":0,"body":"ADD: Honeybrätscher","replies":[]},{"poster":"Durkheim ","date":"2017-09-19T22:55:45.262+0000","up_votes":1,"down_votes":0,"body":"Vielleicht findet ihr was in Südamerika. Da solls noch nen Jungle geben. In wien wirds wohl schwer...","replies":[]}]}