{"poster":"federiquen0113","date":"2017-03-27T10:14:41.180+0000","title":"¿como miercole se saca el la cola de baja prioridad ?","subforum":"Problemas Técnicos","up_votes":4,"down_votes":5,"body":"ayudenme esque soy re nuevo","replies":[{"poster":"9081913DEL1","date":"2017-03-27T10:33:05.750+0000","up_votes":2,"down_votes":1,"body":"Hola!\n\nDeberás jugar unas partidas con esa espera que te indica. Luego de esas pocas partidas vuelves a la normalidad.\n\nSaludos!","replies":[]},{"poster":"iH3RN4Ni","date":"2017-03-27T14:18:55.836+0000","up_votes":1,"down_votes":0,"body":"jugando","replies":[]},{"poster":"Hnk Kenshiro","date":"2017-03-27T12:13:16.759+0000","up_votes":1,"down_votes":0,"body":"Jugando partidas, normalmente 5","replies":[]}]}