{"poster":"sciony1","date":"2015-05-14T15:18:20.226+0000","title":"Creazione squadra ranked","subforum":"Discussioni generali","up_votes":2,"down_votes":3,"body":"Buona pomeriggio a tutti, Sono Sciony1, con un due amici vorremmo creare una squadra per le ranked siamo in cerca di due persone;\r\nSiamo in cerca di questi requisiti:\r\n1. Ovviamente liv 30 con almeno 300 vittorie.\r\n2. Che se la cavi in quasi tutti i ruoli, in particolare nella _**BOT LANE**_.\r\n3. Che parli italiano. \r\n4. Possibilit&agrave; di giocare con frequenza.\r\n**5. CHE SIA PREDISPOSTO AL GIOCO DI SQUADRA. **\r\n{{champion:106}} {{summoner:31}} _**Grazie per la Vostra Attenzione**_  {{summoner:31}} {{champion:106}}","replies":[{"poster":"kirchhoff","date":"2015-07-28T22:00:09.629+0000","up_votes":1,"down_votes":0,"body":"Sezione forum sbagliata.","replies":[]},{"poster":"Marioilnano","date":"2015-05-15T12:15:07.082+0000","up_votes":1,"down_votes":0,"body":"io sono interessato , in game sono Marioilnano , contattatemi se volete :)","replies":[{"poster":"sciony1","date":"2015-07-28T20:38:28.198+0000","up_votes":1,"down_votes":0,"body":"scs il ritardo se sei ancora interessato aggiungimi non sono entrato sul sito xd ( sciony1 )","replies":[]}]}]}