{"poster":"Undead Pho3nix","date":"2015-10-20T16:36:00.602+0000","title":"Is it just me or is the has the server shat itself.","subforum":"[ARCHIVED] Help & Support","up_votes":5,"down_votes":0,"body":"^^Title","replies":[{"poster":"Yolo Swagins","date":"2015-10-20T17:53:56.282+0000","up_votes":2,"down_votes":0,"body":"Just got leaver buster (low priority) for not being able to connect to one game.... awesome...","replies":[]},{"poster":"Undead Pho3nix","date":"2015-10-20T16:42:08.015+0000","up_votes":2,"down_votes":0,"body":"WTF RITO FIX YOUR FKN SHT","replies":[]},{"poster":"Kitakama","date":"2015-10-21T02:03:41.129+0000","up_votes":1,"down_votes":0,"body":"No it's not just you. The server kicked me for 35 minutes in a ranked game. Needless to say I was reported for something riot caused.","replies":[]},{"poster":"Dark Morgana","date":"2015-10-20T22:56:47.483+0000","up_votes":1,"down_votes":0,"body":"You guys may need to try a connection KB to get the issue fixed: https://support.riotgames.com/hc/en-us/articles/201752664-Troubleshooting-Connection-Issues It may be a pain in the keaster but this will more than likely help you with the issue. It helped me when I had the same issue. {{champion:25}} {{summoner:6}} {{item:1026}}","replies":[]},{"poster":"Crêpe","date":"2015-10-20T16:59:51.895+0000","up_votes":1,"down_votes":0,"body":"Bump. can't enter games, servers are buggered","replies":[]},{"poster":"Undead Pho3nix","date":"2015-10-20T16:42:51.685+0000","up_votes":1,"down_votes":0,"body":"DC 5x in a game is NOT OK....it doesnt even RC..just stits there doing fuck all. I have to close client and reconnect every time to get back in my game for like 4 mins till it dcs me again.","replies":[]},{"poster":"Undead Pho3nix","date":"2015-10-20T16:48:24.366+0000","up_votes":1,"down_votes":1,"body":"Ban me for leaving this game and im going to come to your studios and take a fucking hammer to your servers. It might help.","replies":[]}]}