{"poster":"SHRX Sioz","date":"2017-09-24T13:12:10.564+0000","title":"LF FlexQ Team - Plat Tank Jungler","subforum":"Clans & Teams","up_votes":1,"down_votes":0,"body":"Hi ich suche f&uuml;r jetzt ein paar Leute zum spielen. Ich bin Plat 5 in Solo und FlexQ. Shotcalling ist vorhanden. Mains: Seju, Mao, Zac, Cho\r\n\r\nAdd Sioz","replies":[{"poster":"FroggySan","date":"2017-09-24T15:57:25.235+0000","up_votes":1,"down_votes":0,"body":"Ja moin , bauen grad n supp team auf Wenn interesse bitte adden: Gin Extratryhard\ngrüße gin","replies":[]}]}