{"poster":"Brakax ","date":"2017-07-29T05:10:44.897+0000","title":"No puedo conectar !!!!!!!!!!","subforum":"Charlas Generales","up_votes":3,"down_votes":0,"body":"No puedo conectar a mi cuenta reinstale el juego 4 veces y las 4 veces mande reparar use tambien el hexchet repair tools y NADA cuando intento logear me queda en AUTENTICANDO y jamas entra al game. ESPERO QUE ALGUIEN ME AYUDE.\r\n\r\nSALUDOS","replies":[{"poster":"Mr Davidenko","date":"2017-07-29T06:32:20.895+0000","up_votes":1,"down_votes":0,"body":"Manda un ticket a soporte. Probablemente sea que tenes activado el Ipv6, porque me pasaba lo mismo, pero desde soporte van a pedirte tus registros y de ahí te dicen cuáles son los problemas de tu red. Espero haberte ayudado. Saludos!","replies":[]}]}