{"poster":"Laìken","date":"2018-07-24T14:37:42.882+0000","title":"Suche 1-2 Mates für Flex Challenger (momentan D1)","subforum":"Clans & Teams","embed":{"description":"MetaI is Life / Diamond 5 100LP / 154W 126L Win Ratio 55% / Warwick - 32W 24L Win Ratio 57%, Sejuani - 15W 11L Win Ratio 58%, Master Yi - 17W 6L Win Ratio 74%, Jax - 10W 10L Win Ratio 50%, Aurelion Sol - 9W 8L Win Ratio 53%","url":"http://euw.op.gg/summoner/userName=MetaI+is+Life","image":"http://opgg-static.akamaized.net/images/logo/2015/reverse.rectangle.png"},"up_votes":1,"down_votes":0,"body":"Hall&ouml;chen,\r\n\r\nich suche einen oder vlt. zwei Mates f&uuml;r FlexQ - Challenger!\r\n\r\n**zu mir:**\r\n\r\n- Solo Q Dia5/Dia4  55% wr \r\n- Flex Q D1 70% wr\r\n- Allrounder\r\n- Ts sowie gutes Headset vorhanden\r\n- 18 Jahre alt\r\n\r\nzu euch:\r\n\r\n- Solo Q Dia\r\n- Flex Q mind. Plat\r\n- gute winrates \r\n- Lane egal\r\n- alter egal\r\n\r\nBei Interesse oder Fragen k&ouml;nnt ihr mich gern adden :)\r\n\r\nMfG Laiken\r\n{{sticker:slayer-pantheon-thumbs}}","replies":[]}