{"poster":"eMaDDen","date":"2017-03-27T18:20:15.373+0000","title":"Rune e maestrie per Lee Sin | Season7","subforum":"Campioni e gameplay","embed":{"description":"Sono le due di notte e non so cosa fare, allora provo a fare lo Youtubell","url":"https://youtu.be/uuWptG4DFSA","image":"https://i.ytimg.com/vi/uuWptG4DFSA/hqdefault.jpg"},"up_votes":3,"down_votes":2,"body":"Ho fatto questo video per i main lee sin, mi piace l&#039;idea di creare un canale dedicato a questo champ  {{champion:64}} e ad&#039;altro inerente. Fatemi sapere cosa ne pensate thx {{sticker:slayer-jinx-catface}}","replies":[{"poster":"Rakert","date":"2017-06-20T13:22:30.315+0000","up_votes":1,"down_votes":0,"body":"Carino","replies":[]}]}