{"poster":"The Alpha Kitty","date":"2015-12-05T19:09:17.980+0000","title":"Ranked team","subforum":"Csapat- és csapattagkereső","up_votes":1,"down_votes":0,"body":"Sziasztok. Ranked teambe keresek adc-t &eacute;s junglert.  Elv&aacute;r&aacute;saim vannak de nem olyan neh&eacute;z teljesiteni &ouml;ket szerintem. \nAmit a teamr&ouml;l tudni kell :\n- Mid, top, supp foglalt . A mides&uuml;nk szinte kiv&aacute;l&oacute; ( &eacute;s nem az&eacute;rt hogy f&eacute;nyezzem :D ) Nagyon j&oacute;l kommunik&aacute;l a csapattal stb. egyszoval nagyo j&oacute;. a Top laner, szoval &eacute;n SZINTE minden toplanerrel tudok j&aacute;tszani. Vannak hib&aacute;im de m&aacute;r kezdek &quot;kinőni &quot; bel&ouml;ll&uuml;k.\nR&oacute;lam:\n- G&aacute;bornak hivnak 16 &eacute;ves vagyok jelenleg season 3 &oacute;ta j&aacute;tszom NAPI szinten. Top main vagyok 1 &eacute;s f&eacute;l &eacute;ve kb szinte minden  top lanerrel jol tudok j&aacute;tszani. Rengar main vagyok amiota j&aacute;tszok &eacute;s igy &aacute;ltal&aacute;ban ő vele szoktam toppozni ( persze ranked teambe nem hozom folyamatosan :D ). Vannak kisebb kirohan&aacute;saim sőt nagyobbak is de m&aacute;r kezdem abbahagyni. Jelenleg Gold V vagyok j&ouml;v&ouml;re a c&eacute;lom a plat/dia.\nMid laner:\n-19 &eacute;ves 2-3 &eacute;ve j&aacute;tszik jelenleg Diamond V &eacute;s t&eacute;nyleg hozza azt a szintet amit kell. A csapattal j&oacute;l kommunik&aacute;l nem ragel. Hogy milyen champekt szokott hozni az &aacute;ltal&aacute;ban AP-s de assasinal is meg&aacute;lja a hely&eacute;t.\nSupport:\n-Vele lassan 2 &eacute;ve j&aacute;tszom egy&uuml;tt nagyon j&oacute; j&aacute;t&eacute;kos. A csapattal j&oacute;l kommunik&aacute;l f&ouml;leg az adc-vel ha megvan a SZINERDZSII :DD. Thresh main de minden TANKOS supportal j&oacute;l j&aacute;tszik. Ő Gold V  16 &eacute;ves.\nElv&aacute;r&aacute;sok:\n- Nagyon komoly sz&aacute;nd&eacute;kkal hoztam l&eacute;tre ezt a teamet &eacute;s a supportal ill. midessel m&aacute;r j&aacute;tszottam egy&uuml;tt.\n-Minimum Gold V legyen az illet&ouml; &eacute;s legal&aacute;bb 1 &eacute;ves tapasztalata legyen a j&aacute;t&eacute;kkal illetve a adc/jungler posztal is legyen egy f&eacute;l &eacute;ves tapasztalata.\n-Skype legyen.\n- Ne rageljen, de ez tudom hogy lehetetlen valakin&eacute;l szoval eln&eacute;zem ha egy kicsit ragel.\n-16 &eacute;ves legyen minimum.\n-Szinte minden adc-val/Jungle champel tudjon j&aacute;tszani &eacute;s tudja mikor mi a dolga.\n-Napi szinten minimum 2 gamet tudjon j&ouml;nni.\nNagyj&aacute;b&oacute;l mindent elmondtam a t&ouml;bbit ha valami kimaradt skypeon megbesz&eacute;lj&uuml;k. \nUI.: Napi szinten fentvagyok sz&oacute;val b&aacute;rmikor el&eacute;rhető vagyok a nevem : szellemlovas14","replies":[{"poster":"SS Pappino","date":"2015-12-06T09:14:41.072+0000","up_votes":1,"down_votes":0,"body":"Remélem én vagyok a mid xd","replies":[{"poster":"The Alpha Kitty","date":"2015-12-06T09:21:38.832+0000","up_votes":1,"down_votes":0,"body":"Nem. Te csakselejt vagy Kappa :DD","replies":[]}]}]}