{"poster":"MisogiKumagawa","date":"2017-08-18T22:22:13.392+0000","title":"Skin Guardian star","subforum":"Discussioni generali","up_votes":2,"down_votes":1,"body":"Ma solo ahri avr&aacute; il set di frasi cambiato?","replies":[{"poster":"Giorgio di villa","date":"2017-08-18T22:30:30.187+0000","up_votes":1,"down_votes":0,"body":"ahri è una skin leggendaria quindi si, solo lei avrà nuove frasi","replies":[{"poster":"MisogiKumagawa","date":"2017-08-18T22:54:12.519+0000","up_votes":1,"down_votes":0,"body":"È io che speravo in un nuovo set di voci di soraka che non sia lo stesso col filtro  cambiato","replies":[{"poster":"davide1908","date":"2017-08-18T23:33:43.514+0000","up_votes":1,"down_votes":0,"body":"Arriverà anche per soraka una skin leggendaria, si spera, ma quella skin purtroppo non è quella da guardiana stellare...","replies":[{"poster":"Hyρerion","date":"2017-08-19T01:10:28.974+0000","up_votes":2,"down_votes":0,"body":"> [{quoted}](name=davide1908,realm=EUW,application-id=MJVj50Jw,discussion-id=kKqebduV,comment-id=000000000000,timestamp=2017-08-18T23:33:43.514+0000)\n>\n> Arriverà anche per soraka una skin leggendaria, si spera, ma quella skin purtroppo non è quella da guardiana stellare...\n\nIo avrei visto più soraka come leggendaria delle SG, Ahri non è male ma le avrei visto un tema diverso","replies":[{"poster":"HaIIeIujah","date":"2017-08-19T08:21:54.275+0000","up_votes":3,"down_votes":0,"body":"Ahri è una cash cow di proporzioni epocali. Soraka no.","replies":[]},{"poster":"MisogiKumagawa","date":"2017-08-19T08:14:40.304+0000","up_votes":1,"down_votes":0,"body":"Idem","replies":[]}]}]}]}]}]}