{"poster":"Kopperfield1","date":"2015-11-30T21:24:15.203+0000","title":"Silber 3 Main Jungle sucht Team für Season 6","subforum":"Clans & Teams","up_votes":1,"down_votes":0,"body":"Hallo alle zusammen,\r\n\r\nich spiele seit Season 3 LOL und finde mich am besten als Jungler zurecht. Au&szlig;erdem kann man mich auch auf der Toplane gebrauchen. \r\nIch bin ein Tank-Jungler, was ja zur Zeit Meta ist, allerdings kann sich das ja auch bald &auml;ndern, deshalb bin ich froh, wenn jemand konstruktive Vorschl&auml;ge \r\neinbringt und ich andere Jungler lernen kann.\r\n\r\nEin wenig zu mir:\r\n\r\nWie oben schon zu sehen ist, befinde ich mich zur Zeit in Silber 3, strebe jedoch nach h&ouml;herem. Ich bin 22 Jahre alt, geh&ouml;re nicht zu den Flamern in diesem Spiel und bin ansonsten ein eher ruhiger Zeitgenosse, es sei denn, ein Match in LOL packt mich ;)\r\n\r\nWas ich suche ist ein aktives Team, dass noch einen Jungler oder Toplaner sucht, auch  Trainingsabenden oder Wochenenden lassen sich einrichten, \r\nallerdings bin ich bis kurz nach Neujahr zeitlich gebunden, wodurch nur Montag, Mittwoch und das Wochenede zum zocken bleibt.\r\n\r\nFalls sich ein Team angesprochen f&uuml;hlt, added mich ruhig Ingame, \r\nmein Account ist Kopperfield1\r\n\r\nMFG.","replies":[{"poster":"space TempeYEY","date":"2015-12-01T16:14:43.725+0000","up_votes":1,"down_votes":0,"body":"Schau doch einfach mal bei uns vorbei!\n\nHomepage:\n[www.space-multigaming.de](http://space-multigaming.de/)\n\nTeamSpeak3:\n[Hier klicken!](http://ts3server://ts3.space-multigaming.de?port=2086)","replies":[]}]}