{"poster":"Dantazzo","date":"2015-10-10T18:18:03.828+0000","title":"Ode ad un eroe","subforum":"Discussioni generali","up_votes":1,"down_votes":3,"body":"Oggi si chiudeva il girone D, io ero triste perch&egrave; avevo cannato tutti gli abbinamenti, avevo paura di fare 0 punti e di mettere a rischio la seconda adorabile icona porosa {{summoner:31}} , quando arriv&ograve; lui, mi ero scordato di lui, sembrava aver cambiato totalmente livello, ma oggi &egrave; tornato lo stesso di una volta, lo stesso che tutti noi amiamo. Grazie Soaz, sei sempre il mio pippone preferito &lt;3","replies":[{"poster":"StayM","date":"2015-10-10T18:29:22.515+0000","up_votes":1,"down_votes":0,"body":"0/9 the dream, anche io per un attimo ho pensato fosse diventato forte ma per fortuna mi ha smentito <3","replies":[]}]}