{"poster":"SpideyPizza","date":"2016-01-27T11:37:42.620+0000","title":"Video LoL settimanali","subforum":"Discussioni generali","up_votes":2,"down_votes":1,"body":"ma per curiosita&#039;, come mai non ci sono piu&#039; i video settimanali in cui venivano presentate le patch o cosplay, eventi, merch eccc ?\r\nvenivano presentati da [nikkisaur](http://leagueoflegends.wikia.com/wiki/Nika_&#039;Nikasaur&#039;_Harper)\r\n\r\nso che ha abbandonato, ma il progetto era carino, si dovrebbe fare anche con altre persone :D o magari un&#039;idea per il portatle italino, no?","replies":[{"poster":"Nibbio Bianco","date":"2016-01-27T11:52:58.248+0000","up_votes":2,"down_votes":0,"body":"Ha lasciato la riot per dedicarsi alla scrittura. \n\nNira, Frattaglia e la signora del lago. https://static-cdn.jtvnw.net/emoticons/v1/41/1.0","replies":[{"poster":"SpideyPizza","date":"2016-01-27T11:56:03.897+0000","up_votes":1,"down_votes":0,"body":"e lo so >.< pero' sarebbe bello farlo \"sostituendola\"","replies":[]}]}]}