{"poster":"Bizcochitø","date":"2017-10-09T02:53:31.805+0000","title":"Se Busca Gente Para Equipo Oro-Platino","subforum":"Reclutamiento","up_votes":3,"down_votes":1,"body":"Bueno como eh visto varios post de gente que busca equipo tuve esta idea de crear uno , soy main mid platino V asi que si quieres unirte me agregas o comentas , la idea de formar esto es que participemos en torneos y practicar en Colas flex la comunicacion y mec&aacute;nicas dentro del juego (macro-game , los calls , rotaciones , etc)\r\n\r\nRequisitos:\r\n\r\n-Tener Discord \r\n-Ser Oro o +\r\n-No ser flamer\r\n-Ser auto-critico\r\n-Y querer aprender de este infinito y complejo juego \r\n\r\nEso 10/4","replies":[{"poster":"The Start 1","date":"2017-10-09T09:30:28.822+0000","up_votes":1,"down_votes":1,"body":"Agrega \"Este NoEs Suareh\"\n{{sticker:sg-syndra}}","replies":[]},{"poster":"Delightful Agony","date":"2017-10-09T05:58:27.232+0000","up_votes":1,"down_votes":1,"body":"Agregame, tengo un duo (somos bot).","replies":[]},{"poster":"onichan budokai","date":"2017-10-09T03:50:45.354+0000","up_votes":1,"down_votes":1,"body":"agrega jg :)","replies":[]},{"poster":"Navz","date":"2017-10-09T03:18:48.697+0000","up_votes":1,"down_votes":1,"body":"Me anoto! , supp","replies":[]}]}