{"poster":"Little Sunshinee","date":"2016-08-15T10:58:25.320+0000","title":"Lol Funktioniert nicht mehr","subforum":"Hilfe & Support","up_votes":1,"down_votes":0,"body":"Hallo,\r\n\r\nBei mir ist folgendes Problem aufgetreten :\r\n- Wenn ich die Hextech-Werkstatt &ouml;ffnen will schlie&szlig;t sich das spiel immer mit dem Windows Fenster League of legend funktioniert nicht mehr . \r\nHaben andere auch das Problem und kennen eine L&ouml;sung darauf ?\r\nDer Rest funktioniert Problemlos.","replies":[{"poster":"Rïot Alex","date":"2016-08-16T10:55:55.526+0000","up_votes":1,"down_votes":0,"body":"Hilfe!!!! Lol lässt sich nicht mehr im WLAN öffnen, nur noch über Kabelverbindung , was ist da los und hat das etwas mit der Studie WLAN vs Ethernet zu tun??","replies":[]},{"poster":"silibum","date":"2016-08-15T13:17:25.651+0000","up_votes":1,"down_votes":0,"body":"Deaktiviere (beendet) falls vorhanden plays.tv. Das hilft einigen.","replies":[]},{"poster":"YanKYhii","date":"2016-08-15T11:31:41.722+0000","up_votes":1,"down_votes":0,"body":"Das Problem haben viele. \nWurde auch oft genung hier gepostet.","replies":[]}]}