{"poster":"RES Mindless","date":"2019-11-13T15:11:03.674+0000","title":"Little Legends","subforum":"Teamfight Tactics","up_votes":2,"down_votes":0,"body":"Hallo liebe Community,\r\n\r\nWie bekommt man denn eine Little Legend auf Stufe 3? Brauch ich jedesmal den selben z.B Silverwing? Das wäre ja dann eine ziemliche Geldausgabe nur um einen auf diese Stufe zu bekommen oder kann es auch passieren, dass aus einem Ei ein Level 3 Legend rauskommt?\r\n\r\nDanke für die Antworten!\r\n\r\nLG","replies":[{"poster":"Megamaexx","date":"2019-11-13T15:29:19.615+0000","up_votes":2,"down_votes":0,"body":"Soweit ich weiß, musst du ein und denselben wirklich 3x gezogen haben. Wie das bei denen aussieht, die man auch direkt kaufen kann, weiß ich nicht, da reicht aber wahrscheinlich 3x kaufen","replies":[{"poster":"RES Mindless","date":"2019-11-13T15:36:28.380+0000","up_votes":1,"down_votes":0,"body":"Uff, dann muss man ja immer, die Random Eier kaufen und hoffen, dass 3x der Selbe dabei rauskommt.","replies":[{"poster":"Enderized","date":"2019-11-13T17:31:34.969+0000","up_votes":3,"down_votes":0,"body":"So ist das- und für den Preis der Schätzchen, so süß sie teilweise auch sind... sehe ich ja nicht ein :D","replies":[]}]}]},{"poster":"Phoenixale","date":"2019-11-14T00:47:06.590+0000","up_votes":2,"down_votes":0,"body":"Die hätten mal lieber die Minions als Standardset rausbringen sollen :P","replies":[{"poster":"RES Mindless","date":"2019-11-14T09:19:52.682+0000","up_votes":1,"down_votes":0,"body":"Ja was für eine super Idee *-* Einfach die kleinen Caster Minions bitte!\n{{sticker:sg-lux}}","replies":[]}]}]}