{"poster":"Aizu Tempest","date":"2016-02-19T10:00:54.067+0000","title":"Insane Ahri","subforum":"Skin- & Champion-Konzepte","embed":{"description":null,"url":"http://i.imgur.com/TtkNy.jpg","image":"http://imgur.com/TtkNys.jpg"},"up_votes":2,"down_votes":2,"body":"Ich finde wir brauchen nen neuen Ahri Skin. {{champion:103}}   ^^","replies":[{"poster":"Ahri NineTailFox","date":"2016-05-27T12:33:42.748+0000","up_votes":1,"down_votes":0,"body":"Mir gefällt der Skin würde mich endlich über einen Legendary oder Ultimate Ahri skin Freuen ...","replies":[]},{"poster":"Zero000","date":"2016-02-19T11:43:31.892+0000","up_votes":1,"down_votes":0,"body":"Das ganze sieht zwar nicht schlecht aus, aber mir fehlt irgendwie das Thema, nach \"Insane \" sieht es zumindest nicht aus.","replies":[]},{"poster":"Samuraisub","date":"2016-02-19T11:29:46.323+0000","up_votes":1,"down_votes":0,"body":"Nice","replies":[]},{"poster":"Alustus","date":"2016-02-19T10:40:35.910+0000","up_votes":1,"down_votes":0,"body":"Grundsätzlich habe ich nichts gegen neue Skins, aber Ahri wurde in letzter Zeit in dieser Hinsicht meiner Meinung nach genug ausgestattet.\n\nChallanger Ahri\nAkademie Ahri sind noch ziemlich neu, da gibts einige Champs die schon länger nichts mehr abbekommen haben, bei denen mir ein neuer Skin auch gefallen würde ;)","replies":[{"poster":"p0hil","date":"2016-02-19T11:23:03.126+0000","up_votes":1,"down_votes":0,"body":"{{champion:83}} Kappa.","replies":[]}]},{"poster":"Aizu Tempest","date":"2016-02-19T11:04:13.117+0000","up_votes":1,"down_votes":0,"body":"Naja, er mss ja auch nicht gleich kommen.^^ Würde sowieso alles ein weilchen dauern habe ja auch auch Vorschlag für Winter/ Weihnachten gemacht. :D","replies":[]}]}