{"poster":"Schàdenfreude","date":"2016-08-04T16:57:46.232+0000","title":"How to check your ping before you play a game.","subforum":"Gameplay","up_votes":3,"down_votes":7,"body":"1. Type &quot;cm&quot; in search bar.\r\n2. Open Command Prompt.\r\n3. type in &quot;ping google.ca&quot; (or any other website).\r\n4. It should display your ping milliseconds to you.\r\n\r\nHope this helps!","replies":[{"poster":"Deep Terror Nami","date":"2016-08-04T17:13:30.191+0000","up_votes":4,"down_votes":0,"body":"I just use a simple batch file I created on my desktop;\n\n> ping 104.160.131.1 -t\n\nThe NA game server is actually **192.64.170.1** (found on the [Network](https://support.riotgames.com/hc/en-us/articles/201752674-Network-System-and-League-of-Legends-Logs) kb article), but Riot tightly controls pings to it so you'll frequently not get a reply. The server IP I use is a hop just before that and will respond normally.","replies":[]},{"poster":"WrÆth","date":"2016-08-04T17:03:32.842+0000","up_votes":2,"down_votes":0,"body":"This guide you talked about displays your ping to google. Not your ping to league of legends. Instead of ping google.ca type ping na.leagueoflegends.com","replies":[{"poster":"Schàdenfreude","date":"2016-08-04T17:33:56.056+0000","up_votes":1,"down_votes":1,"body":"It's still about the same tho for meh. The ping i mean so i usually just do google.ca","replies":[]}]},{"poster":"Aelyn","date":"2016-08-04T17:02:12.797+0000","up_votes":1,"down_votes":1,"body":"***","replies":[{"poster":"ntbcool","date":"2016-08-04T19:04:40.365+0000","up_votes":1,"down_votes":0,"body":"Why would you switch servers? If you live in Romania then you should stay on the EUNE server, Na Server is obviously in North America (Chicago) and the EUNE is in Amsterdam....... Kinda of the point of having different servers, the only ones your probably will have ok ping on would be EUW and EUNE","replies":[{"poster":"Aelyn","date":"2016-08-04T19:13:14.463+0000","up_votes":2,"down_votes":1,"body":"***","replies":[{"poster":"ntbcool","date":"2016-08-04T19:29:45.350+0000","up_votes":1,"down_votes":0,"body":"The reason i posted is cause it seems as if you have no clue how the separate servers work...... \n> i transfered from eune where i had 50. to na where i have 150.. \n\nNo duh your ping would drop drastically, so I obviously assumed you had no clue how it worked and decided to give you some insight..... even told you which servers you will have a better chance on ping wise (full list with locations here: jk to lazy find it yourself)","replies":[]},{"poster":"Ok sure but why","date":"2016-08-04T20:28:02.907+0000","up_votes":1,"down_votes":0,"body":"Well, it is pretty bs.","replies":[]}]}]},{"poster":"Eunson","date":"2016-08-04T17:17:44.614+0000","up_votes":1,"down_votes":0,"body":"Move closer to the servers","replies":[{"poster":"Aelyn","date":"2016-08-04T17:30:22.479+0000","up_votes":1,"down_votes":0,"body":"***","replies":[{"poster":"Eunson","date":"2016-08-04T17:36:04.140+0000","up_votes":1,"down_votes":1,"body":"SOL then :D Welcome to NA server issues where anyone not East coast has 150 ping themselves.","replies":[{"poster":"Aelyn","date":"2016-08-04T18:00:30.588+0000","up_votes":1,"down_votes":0,"body":"***","replies":[{"poster":"Eunson","date":"2016-08-04T18:16:44.418+0000","up_votes":1,"down_votes":0,"body":"People that live in NA range from 15-200 ping depending on where they live. NA is massive and has 1 server location while other smaller locations have 4 servers...the population just isn't here for it.","replies":[]}]}]}]}]}]},{"poster":"Reikken","date":"2016-08-04T19:34:13.825+0000","up_votes":1,"down_votes":0,"body":"ping to google is different from ping to LoL\n\ngoogle has servers everywhere, so you'll usually have a better ping to google","replies":[]},{"poster":"1wolfpack","date":"2016-08-04T18:45:46.880+0000","up_votes":1,"down_votes":0,"body":"usually I create a custom 1v1 game vs bot,\nif everything runs smoothly, exit match and jump into ranked","replies":[]},{"poster":"AcidTheWarlock","date":"2016-08-04T16:59:51.268+0000","up_votes":1,"down_votes":0,"body":"Thanks! This helps a lot since my connection can be at 3000 ping or 15, it really depends.","replies":[{"poster":"Hyperiön","date":"2016-08-04T17:04:33.045+0000","up_votes":1,"down_votes":0,"body":"Better router should mostly get rid of that problem, if you are hardwired, then... well you need a new modem xD","replies":[{"poster":"AcidTheWarlock","date":"2016-08-04T17:16:41.652+0000","up_votes":1,"down_votes":0,"body":"Yeah, my router is actually really old lol","replies":[{"poster":"Hyperiön","date":"2016-08-04T17:30:42.563+0000","up_votes":1,"down_votes":0,"body":"SHould definitely look into upgrading that :)","replies":[]}]}]}]},{"poster":"HeroineSam","date":"2016-08-04T17:11:23.084+0000","up_votes":1,"down_votes":0,"body":"Also, is lower ping better than higher ping? And what does ping affect? How smoothly the game plays?","replies":[{"poster":"Raven Elizabeth","date":"2016-08-04T17:22:04.993+0000","up_votes":1,"down_votes":0,"body":"Yes the lower the ms(ping) the better. Internet speeds, Type of modem/router, your computer and the amount of things on the network can affect it. having 40-50 ping is makes the game run smooth as silk as long as you have decent FPS","replies":[]}]},{"poster":"Eunson","date":"2016-08-04T17:16:29.125+0000","up_votes":1,"down_votes":0,"body":"1. Type \"CMD\"\n2. ping google.ca (8.8.8.8) will ping google...it won't tell you your ping to League servers... Ping the League servers and that'll give you your ping.","replies":[]},{"poster":"Kaioko","date":"2016-08-04T17:01:18.209+0000","up_votes":1,"down_votes":0,"body":"I would add - when you type \"ping www.google.com\" to actually type \"ping www.google.com -t -l 1200\" those pings will be a lot closer to simulating gaming related ones.","replies":[]},{"poster":"GodArmTV","date":"2017-09-19T06:29:29.290+0000","up_votes":1,"down_votes":1,"body":"i literally uninstalled mcafee and i allowed lol through the firewall and now im at 60 ping same as my desktop using laptop used to lag ping 350 now its perfect goodluck guys","replies":[]}]}